[
  {
    "id": "boss_intro_early",
    "speaker": "rival",
    "text": "dialogues_boss_intro_early_text",
    "tags": ["boss_intro"],
    "priority": 90,
    "conditions": { "min_run": 0, "max_run": 1, "flags_required": [], "flags_forbidden": [] },
    "once_per_run": true
  },
  {
    "id": "boss_taunt",
    "speaker": "rival",
    "text": "dialogues_boss_taunt_text",
    "tags": ["boss_intro"],
    "priority": 50,
    "once_per_run": true
  },
  {
    "id": "boss_tired",
    "speaker": "rival",
    "text": "dialogues_boss_tired_text",
    "tags": ["boss_intro"],
    "priority": 80,
    "conditions": { "min_run": 5, "max_run": 999, "flags_required": [], "flags_forbidden": [] },
    "once_per_run": true
  },
  {
    "id": "boss_defeat_gloat",
    "speaker": "rival",
    "text": "dialogues_boss_defeat_gloat_text",
    "tags": ["player_defeated"],
    "priority": 10,
    "once_per_run": true
  },
  {
    "id": "boss_player_wins",
    "speaker": "rival",
    "text": "dialogues_boss_player_wins_text",
    "tags": ["player_won"],
    "priority": 10,
    "once_per_run": true
  }
]
