{
  "id": "sting",
  "name": "sting_name",
  "tooltip": "sting_tooltip",
  "desc": "sting_desc",
  "icon": "icons/skills/sting.png",
  "cooldown": 1,
  "behaviour_tags": [
    "melee",
    "damage"
  ],
  "mood": [
    "burnout"
  ],
  "level": 1,
  "abilities": [
    {
      "id": "direct_melee_damage",
      "sound_start": "direct_melee_damage/direct_melee_damage_start.wav",
      "collision_effect": "direct_melee_damage/direct_melee_damage_collision.prefab",
      "sound_end": "direct_melee_damage/direct_melee_damage_end.wav",
      "animation": "direct_melee_damage/direct_melee_damage.anim",
      "target": {
        "kind": "actor",
        "range": 1
      },
      "area": {
        "kind": "chain",
        "max_chain_length": 1
      },
      "effects": [
        {
          "damage": 7
        }
      ]
    },
    {
      "id": "apply_poison_single",
      "sound_start": "apply_poison_single/apply_poison_single_start.wav",
      "collision_effect": "apply_poison_single/apply_poison_single_collision.prefab",
      "sound_end": "apply_poison_single/apply_poison_single_end.wav",
      "animation": "apply_poison_single/apply_poison_single.anim",
      "target": {
        "kind": "actor",
        "range": 2
      },
      "area": {
        "kind": "chain",
        "max_chain_length": 1
      },
      "effects": [
        {
          "damage": 3,
          "status_id": "poisoned(3)"
        }
      ]
    }
  ]
}